django_rest_passwordreset/__init__.py
django_rest_passwordreset/admin.py
django_rest_passwordreset/models.py
django_rest_passwordreset/serializers.py
django_rest_passwordreset/signals.py
django_rest_passwordreset/tokens.py
django_rest_passwordreset/urls.py
django_rest_passwordreset/views.py
django_rest_passwordreset/management/__init__.py
django_rest_passwordreset/management/commands/__init__.py
django_rest_passwordreset/management/commands/clearresetpasswodtokens.py
django_rest_passwordreset/migrations/0001_initial.py
django_rest_passwordreset/migrations/0002_pk_migration.py
django_rest_passwordreset/migrations/0003_allow_blank_and_null_fields.py
django_rest_passwordreset/migrations/__init__.py
tests/__init__.py
tests/manage.py
tests/settings.py
tests/urls.py
tests/test/__init__.py
tests/test/helpers.py
tests/test/test_auth_test_case.py
tests/test/test_token_generators.py
django_rest_passwordreset-1.3.0.dist-info/LICENSE
django_rest_passwordreset-1.3.0.dist-info/METADATA
django_rest_passwordreset-1.3.0.dist-info/WHEEL
django_rest_passwordreset-1.3.0.dist-info/top_level.txt
django_rest_passwordreset-1.3.0.dist-info/RECORD
